{
  "version": "1.1.0-uat.0",
  "branch": "chore/hl7-v2-version-1.1.0",
  "sourceHash": "ee53f317cdbe90a30f2a1e0113a17cf3101735b0302a4667360f92e2d70aac09",
  "testHash": "e3b0c44298fc1c149afbf4c8996fb92427ae41e4649b934ca495991b7852b855",
  "tasks": {
    "validate": "passed",
    "lint": "passed",
    "compile": "passed",
    "test": "passed",
    "testDirect": "passed",
    "testDocker": "passed",
    "testDataloader": "passed",
    "buildArtifacts": "passed"
  },
  "tests": {
      "unit": { "expected": 0, "ran": 0, "status": "skipped" },
      "integration": { "expected": 0, "ran": 0, "status": "skipped" },
      "e2e": { "expected": 0, "ran": 0, "status": "skipped" }
  }
}
